x64dbg/__init__.py
x64dbg-1.1.0.dist-info/LICENSE
x64dbg-1.1.0.dist-info/METADATA
x64dbg-1.1.0.dist-info/WHEEL
x64dbg-1.1.0.dist-info/top_level.txt
x64dbg-1.1.0.dist-info/RECORD
