Metadata-Version: 2.1
Name: x64dbg
Version: 1.1.0
Summary: An automated testing plugin developed for the x64dbg debugger, used to quickly build Python based test scripts to accelerate the development of exploit programs, assist in vulnerability mining, and analyze malware.
Home-page: http://lyscript.lyshark.com
Author: lyshark
Author-email: me@lyshark.com
License: MIT Licence
Platform: any
Classifier: Programming Language :: Python :: 3
Classifier: License :: OSI Approved :: MIT License
Classifier: Operating System :: OS Independent
Requires-Python: >=3.6.0
License-File: LICENSE
